tabtransformertf/__init__.py
tabtransformertf/models/__init__.py
tabtransformertf/models/embeddings.py
tabtransformertf/models/fttransformer.py
tabtransformertf/models/tabtransformer.py
tabtransformertf/utils/__init__.py
tabtransformertf/utils/helper.py
tabtransformertf/utils/preprocessing.py
tabtransformertf-0.0.8.dist-info/LICENSE
tabtransformertf-0.0.8.dist-info/METADATA
tabtransformertf-0.0.8.dist-info/WHEEL
tabtransformertf-0.0.8.dist-info/top_level.txt
tabtransformertf-0.0.8.dist-info/RECORD
