Metadata-Version: 2.1
Name: tabtransformertf
Version: 0.0.8
Summary: Tab Transformer - TensorFlow
Author: Antons Ruberts
Author-email: rubertant@gmail.com
License: MIT
Keywords: artificial intelligence,transformers,attention mechanism,tabular data
Classifier: Development Status :: 4 - Beta
Classifier: Intended Audience :: Developers
Classifier: Topic :: Scientific/Engineering :: Artificial Intelligence
Classifier: License :: OSI Approved :: MIT License
Classifier: Programming Language :: Python :: 3.6
License-File: LICENSE
Requires-Dist: tensorflow (>=2.6.2)
Requires-Dist: pandas (>=1.1.1)
Requires-Dist: numpy (>=1.19.5)
Requires-Dist: tqdm (>=4.64.0)
Requires-Dist: scikit-learn (>=0.19.0)
